Metadata-Version: 2.1
Name: wsgirpc
Version: 1.0.0
Summary: Tiny implementation of a WSGI-based RPC server and client
Home-page: https://github.com/luismsgomes/wsgirpc
Author: Luís Gomes
Author-email: luismsgomes@gmail.com
License: MIT
Platform: UNKNOWN
Classifier: Development Status :: 5 - Production/Stable
Classifier: License :: OSI Approved :: MIT License
Classifier: Programming Language :: Python :: 3
